zebubot/__init__.py
zebubot/__main__.py
zebubot/cli.py
zebubot/cli_backup.py
zebubot/config.py
zebubot/core.py
zebubot/executor.py
zebubot/myntapi_integration.py
zebubot/noren.py
zebubot/realtime_executor.py
zebubot/symbol_manager.py
zebubot/scripts/__init__.py
zebubot/scripts/myntapi_rsi_optimized.py
zebubot/scripts/option_trading_strategy.py
zebubot-0.0.1b6.dist-info/licenses/LICENSE
zebubot-0.0.1b6.dist-info/METADATA
zebubot-0.0.1b6.dist-info/WHEEL
zebubot-0.0.1b6.dist-info/entry_points.txt
zebubot-0.0.1b6.dist-info/top_level.txt
zebubot-0.0.1b6.dist-info/RECORD
