Metadata-Version: 2.4
Name: zebubot
Version: 0.0.1b6
Summary: A high-performance algorithmic trading platform for Indian stock markets
Author: Zebu Team
Author-email: Zebu Team <it@zebuetrade.com>
License: MIT
Project-URL: Homepage, https://github.com/zebubot/zebubot
Project-URL: Repository, https://github.com/zebubot/zebubot.git
Project-URL: Issues, https://github.com/zebubot/zebubot/issues
Classifier: Development Status :: 4 - Beta
Classifier: Intended Audience :: Financial and Insurance Industry
Classifier: Topic :: Office/Business :: Financial :: Investment
Classifier: License :: OSI Approved :: MIT License
Classifier: Programming Language :: Python :: 3
Classifier: Programming Language :: Python :: 3.8
Classifier: Programming Language :: Python :: 3.9
Classifier: Programming Language :: Python :: 3.10
Classifier: Programming Language :: Python :: 3.11
Classifier: Programming Language :: Python :: 3.12
Classifier: Operating System :: OS Independent
Requires-Python: >=3.8
License-File: LICENSE
Requires-Dist: click>=8.0.0
Requires-Dist: requests>=2.25.0
Requires-Dist: python-dotenv>=0.19.0
Requires-Dist: pyyaml>=6.0
Requires-Dist: pandas>=1.3.0
Requires-Dist: numpy>=1.21.0
Requires-Dist: websockets>=10.0
Requires-Dist: asyncio-mqtt>=0.11.0
Requires-Dist: websocket-client>=1.0.0
Requires-Dist: cython>=0.29.0
Provides-Extra: dev
Requires-Dist: pytest>=6.0; extra == "dev"
Requires-Dist: pytest-cov>=2.0; extra == "dev"
Requires-Dist: black>=21.0; extra == "dev"
Requires-Dist: flake8>=3.9; extra == "dev"
Requires-Dist: mypy>=0.910; extra == "dev"
Dynamic: author
Dynamic: license-file
Dynamic: requires-python
